funnyapi/__init__.py
funnyapi/core.py
funnyapi/periodic.py
funnyapi-0.5.2.dist-info/METADATA
funnyapi-0.5.2.dist-info/WHEEL
funnyapi-0.5.2.dist-info/top_level.txt
funnyapi-0.5.2.dist-info/RECORD
