Metadata-Version: 2.1
Name: funnyapi
Version: 0.5.2
Summary: A fun API for generating jokes and funny facts
Home-page: https://github.com/kseniaris/funnyapi
Author: Ksusha
Author-email: YlC9L@example.com
Requires-Python: >=3.6
